forgehtmx/__init__.py
forgehtmx/static/htmx/forgehtmx.js
forgehtmx/static/htmx/htmx.min.js
forgehtmx/templates/htmx/js.html
forgehtmx/templatetags/__init__.py
forgehtmx/templatetags/htmx.py
forgehtmx/views.py
forge_htmx-0.4.0.dist-info/LICENSE
forge_htmx-0.4.0.dist-info/METADATA
forge_htmx-0.4.0.dist-info/WHEEL
forge_htmx-0.4.0.dist-info/RECORD
